shop/__init__.py
shop/__main__.py
shop/exceptions.py
shop/server.py
shop/snapshot.py
shop/svm.py
shop_vc-0.0.2.dist-info/entry_points.txt
shop_vc-0.0.2.dist-info/WHEEL
shop_vc-0.0.2.dist-info/METADATA
shop_vc-0.0.2.dist-info/RECORD
