Metadata-Version: 2.1
Name: shop-vc
Version: 0.0.2
Summary: Shop, the simple version controller.
Home-page: UNKNOWN
License: UNKNOWN
Author: Pradhyum R
Author-email: drpradhyum2016@outlook.com
Classifier: License :: OSI Approved :: MIT License
Requires-Dist: click
Requires-Dist: halo
Requires-Dist: pyinquirer
Requires-Dist: rich
